amzn_micro_coral/__init__.py
amzn_micro_coral/auth/__init__.py
amzn_micro_coral/auth/base.py
amzn_micro_coral/auth/dummy.py
amzn_micro_coral/auth/midway.py
amzn_micro_coral/auth/sigv4.py
amzn_micro_coral/clients/__init__.py
amzn_micro_coral/clients/crux.py
amzn_micro_coral/py.typed
amzn_micro_coral/service.py
amzn_micro_coral/util/__init__.py
amzn_micro_coral/util/http_sentry_auth.py
amzn_micro_coral-1.0.0.dist-info/METADATA
amzn_micro_coral-1.0.0.dist-info/WHEEL
amzn_micro_coral-1.0.0.dist-info/RECORD
