Metadata-Version: 2.1
Name: amzn-micro-coral
Version: 1.0.0
Summary: Minimal Coral interface for when you can't use a prepackaged client.
Author: Chad Crawford
Author-email: chadcr@amazon.com
Requires-Python: >=3.8,<4.0
Classifier: Programming Language :: Python :: 3
Classifier: Programming Language :: Python :: 3.8
Classifier: Programming Language :: Python :: 3.9
Classifier: Programming Language :: Python :: 3.10
Classifier: Programming Language :: Python :: 3.11
Provides-Extra: midway
Provides-Extra: sigv4
Requires-Dist: boto3 (>=1.28.37,<2.0.0) ; extra == "sigv4"
Requires-Dist: cached-property (>=1.5.2,<2.0.0)
Requires-Dist: requests (>=2.31.0,<3.0.0)
Requires-Dist: requests-auth-aws-sigv4 (>=0.7,<0.8) ; extra == "sigv4"
Requires-Dist: requests-kerberos (>=0.14.0,<0.15.0) ; extra == "midway"
